bigquerypipeline
