Metadata-Version: 2.1
Name: scrapy-bigquery
Version: 1.0.10
Summary: Scrapy pipeline to store items into BigQuery
Home-page: https://github.com/8W9aG/scrapy-bigquery
Author: Will Sackfield
Author-email: will.sackfield@gmail.com
License: MIT
Keywords: scrapy pipeline bigquery
Platform: UNKNOWN
Classifier: License :: OSI Approved :: MIT License
Classifier: Programming Language :: Python :: 3
Classifier: Framework :: Scrapy
